CeLEry/ClusterVAE.py
CeLEry/DNN.py
CeLEry/TrainerExe.py
CeLEry/__init__.py
CeLEry/data_augmentation.py
CeLEry/datasetgenemap.py
CeLEry/fit_functions.py
CeLEry/layers.py
CeLEry/types_.py
CeLEry/util.py
CeLEry/util_Mouse.py
CeLEryPy-1.2.1.dist-info/LICENSE
CeLEryPy-1.2.1.dist-info/METADATA
CeLEryPy-1.2.1.dist-info/WHEEL
CeLEryPy-1.2.1.dist-info/top_level.txt
CeLEryPy-1.2.1.dist-info/RECORD
