Metadata-Version: 2.1
Name: CeLEryPy
Version: 1.2.1
Summary: Leverage spatial transcriptomics data to recover cell locations in single-cell RNA RNA-seq
Author-email: Qihuang Zhang <qihuang.zh@gmail.com>
License: Copyright (c) 2022 The Python Packaging Authority
Project-URL: Homepage, https://github.com/QihuangZhang/CeLEry
Keywords: CeLEry,spatial transcriptomics,scRNA-seq
Classifier: License :: OSI Approved :: MIT License
Classifier: Programming Language :: Python
Classifier: Programming Language :: Python :: 3
Requires-Python: >=3.8
License-File: LICENSE
Requires-Dist: torch >=1.8
Requires-Dist: pandas >=1.4
Requires-Dist: numpy >=1.20
Requires-Dist: scipy
Requires-Dist: tqdm
Requires-Dist: scanpy >=1.5
Requires-Dist: scikit-image
Requires-Dist: anndata
Requires-Dist: scikit-learn
